Metadata-Version: 2.1
Name: tradingview-ta1
Version: 3.2.5
Summary: Unofficial TradingView technical analysis API wrapper.
Home-page: https://github.com/mohamedraslan85/python-tradingview-ta/
Author: mraslan
Author-email: brian@brianthe.dev
License: UNKNOWN
Project-URL: Demo, https://tradingview.brianthe.dev
Project-URL: Documentation, https://python-tradingview-ta.readthedocs.io
Project-URL: Source, https://github.com/mohamedraslan85/python-tradingview-ta/
Platform: UNKNOWN
Classifier: Programming Language :: Python :: 3
Classifier: License :: OSI Approved :: MIT License
Classifier: Operating System :: OS Independent
Requires-Python: >=3.5
Requires-Dist: requests
